README.md
setup.cfg
setup.py
kopt/__init__.py
kopt/config.py
kopt/eval_metrics.py
kopt/hyopt.py
kopt/model_data.py
kopt/utils.py
kopt.egg-info/PKG-INFO
kopt.egg-info/SOURCES.txt
kopt.egg-info/dependency_links.txt
kopt.egg-info/not-zip-safe
kopt.egg-info/requires.txt
kopt.egg-info/top_level.txt
tests/__init__.py
tests/data.py
tests/model.py
tests/test_config.py
tests/test_hyopt.py