Metadata-Version: 1.0
Name: kopt
Version: 0.1.0
Summary: Keras-hyperopt (kopt); Hyper-parameter tuning for Keras using hyperopt.
Home-page: https://github.com/avsecz/keras-hyperopt
Author: Žiga Avsec
Author-email: avsec@in.tum.de
License: MIT license
Keywords: hyper-parameter tuning,keras,deep learning,tensorflow
Platform: UNKNOWN
